ai_chat_manager/__init__.py
ai_chat_manager/py.typed
ai_chat_manager/backends/__init__.py
ai_chat_manager/backends/base.py
ai_chat_manager/backends/elevenlabs_backend.py
ai_chat_manager/backends/huggingface_backend.py
ai_chat_manager/backends/openai_backend.py
ai_chat_manager/backends/venice_backend.py
ai_chat_manager/cli/__init__.py
ai_chat_manager/cli/main.py
ai_chat_manager/cli/wrapper.py
ai_chat_manager/core/__init__.py
ai_chat_manager/core/bot.py
ai_chat_manager/core/config.py
ai_chat_manager/core/enhanced_bot_creation.py
ai_chat_manager/core/exceptions.py
ai_chat_manager/core/manager.py
ai_chat_manager/core/practical_implementation.py
ai_chat_manager/core/types.py
ai_chat_manager/examples/__init__.py
ai_chat_manager/examples/advanced.py
ai_chat_manager/examples/basic.py
ai_chat_manager/utils/__init__.py
ai_chat_manager/utils/helpers.py
cybercore_ai_chat_manager-1.0.4.dist-info/licenses/LICENSE
cybercore_ai_chat_manager-1.0.4.dist-info/METADATA
cybercore_ai_chat_manager-1.0.4.dist-info/WHEEL
cybercore_ai_chat_manager-1.0.4.dist-info/entry_points.txt
cybercore_ai_chat_manager-1.0.4.dist-info/top_level.txt
cybercore_ai_chat_manager-1.0.4.dist-info/RECORD
