Metadata-Version: 2.4
Name: cybercore-ai-chat-manager
Version: 1.0.4
Summary: A modular AI API/chat manager supporting multiple backends
Home-page: https://github.com/TeamMalina/CyberCore
Author: TeamMalina
Author-email: contact@teammalina.dev
License: MIT
Project-URL: Homepage, https://github.com/TeamMalina/CyberCore
Project-URL: Repository, https://github.com/TeamMalina/CyberCore
Project-URL: Documentation, https://github.com/TeamMalina/CyberCore/wiki
Project-URL: Bug Reports, https://github.com/TeamMalina/CyberCore/issues
Project-URL: Changelog, https://github.com/TeamMalina/CyberCore/blob/main/CHANGELOG.md
Keywords: ai chat bot openai api machine-learning nlp chatbot assistant
Classifier: Development Status :: 4 - Beta
Classifier: Intended Audience :: Developers
Classifier: Intended Audience :: Science/Research
Classifier: License :: OSI Approved :: MIT License
Classifier: Operating System :: OS Independent
Classifier: Programming Language :: Python :: 3
Classifier: Programming Language :: Python :: 3.8
Classifier: Programming Language :: Python :: 3.9
Classifier: Programming Language :: Python :: 3.10
Classifier: Programming Language :: Python :: 3.11
Classifier: Programming Language :: Python :: 3.12
Classifier: Topic :: Scientific/Engineering :: Artificial Intelligence
Classifier: Topic :: Software Development :: Libraries :: Python Modules
Classifier: Topic :: Communications :: Chat
Requires-Python: >=3.8
License-File: LICENSE
Requires-Dist: aiohttp<4.0.0,>=3.8.0
Requires-Dist: requests<3.0.0,>=2.31.0
Requires-Dist: httpx<1.0.0,>=0.24.0
Requires-Dist: pydantic<3.0.0,>=2.0.0
Requires-Dist: pydantic-settings<3.0.0,>=2.0.0
Requires-Dist: python-dotenv<2.0.0,>=1.0.0
Requires-Dist: pyyaml<7.0,>=6.0
Requires-Dist: cryptography<42.0.0,>=41.0.0
Requires-Dist: click<9.0.0,>=8.1.0
Requires-Dist: rich<14.0.0,>=13.0.0
Requires-Dist: prompt-toolkit<4.0.0,>=3.0.0
Requires-Dist: python-dateutil<3.0.0,>=2.8.0
Requires-Dist: tiktoken<1.0.0,>=0.5.0
Requires-Dist: tenacity<9.0.0,>=8.0.0
Requires-Dist: typing-extensions<5.0.0,>=4.5.0
Provides-Extra: dev
Requires-Dist: pytest>=7.0.0; extra == "dev"
Requires-Dist: pytest-cov>=4.0.0; extra == "dev"
Requires-Dist: pytest-asyncio>=0.21.0; extra == "dev"
Requires-Dist: black>=23.0.0; extra == "dev"
Requires-Dist: isort>=5.12.0; extra == "dev"
Requires-Dist: flake8>=6.0.0; extra == "dev"
Requires-Dist: mypy>=1.0.0; extra == "dev"
Requires-Dist: pre-commit>=3.0.0; extra == "dev"
Provides-Extra: audio
Requires-Dist: elevenlabs>=0.2.0; extra == "audio"
Requires-Dist: pydub>=0.25.0; extra == "audio"
Requires-Dist: soundfile>=0.12.0; extra == "audio"
Provides-Extra: local
Requires-Dist: torch>=2.0.0; extra == "local"
Requires-Dist: transformers>=4.25.0; extra == "local"
Requires-Dist: accelerate>=0.20.0; extra == "local"
Provides-Extra: all
Requires-Dist: torch>=2.0.0; extra == "all"
Requires-Dist: transformers>=4.25.0; extra == "all"
Requires-Dist: elevenlabs>=0.2.0; extra == "all"
Requires-Dist: openai>=1.0.0; extra == "all"
Requires-Dist: anthropic>=0.3.0; extra == "all"
Dynamic: author
Dynamic: author-email
Dynamic: classifier
Dynamic: description
Dynamic: description-content-type
Dynamic: home-page
Dynamic: keywords
Dynamic: license
Dynamic: license-file
Dynamic: project-url
Dynamic: provides-extra
Dynamic: requires-dist
Dynamic: requires-python
Dynamic: summary
